nfc_uid/__init__.py
nfc_uid/nfc_uid.py
nfc_uid-0.5.dist-info/LICENSE
nfc_uid-0.5.dist-info/METADATA
nfc_uid-0.5.dist-info/WHEEL
nfc_uid-0.5.dist-info/top_level.txt
nfc_uid-0.5.dist-info/RECORD
