Metadata-Version: 2.1
Name: nfc-uid
Version: 0.5
Summary: Get UUID of NFC card with a scanner.
Home-page: https://github.com/Z3R0-CDS/NFC_UID
Author: Zero Codes
Classifier: Development Status :: 4 - Beta
Classifier: Intended Audience :: Science/Research
Classifier: Natural Language :: English
Classifier: Operating System :: Microsoft :: Windows :: Windows 10
Classifier: Programming Language :: Python :: 3.7
Classifier: License :: OSI Approved :: GNU Affero General Public License v3
Requires-Python: >=3.7
License-File: LICENSE
